request_context_manager.py
request_context_manager-0.0.3.dist-info/LICENSE
request_context_manager-0.0.3.dist-info/WHEEL
request_context_manager-0.0.3.dist-info/METADATA
request_context_manager-0.0.3.dist-info/RECORD
