Metadata-Version: 2.1
Name: request_context_manager
Version: 0.0.3
Summary: A easy way to manage resource within request context
Keywords: json,validate,validator
Author-email: Eva Cheng <blue800415@gmail.com>
Requires-Python: >=3.6
Classifier: License :: OSI Approved :: MIT License
Classifier: Operating System :: OS Independent
Classifier: Programming Language :: Python :: 3
Classifier: Programming Language :: Python :: 3.6
Classifier: Programming Language :: Python :: 3.7
Classifier: Programming Language :: Python :: 3.8
Classifier: Programming Language :: Python :: 3.9
Classifier: Programming Language :: Python :: 3.10
Requires-Dist: flit ; extra == "publish"
Requires-Dist: pytest ; extra == "test"
Requires-Dist: pytest-cov ; extra == "test"
Requires-Dist: coverage-lcov ; extra == "test"
Project-URL: Home, https://github.com/8thEdition/request_context_manager.git
Provides-Extra: publish
Provides-Extra: test
